Pyrebase-3.0.26.dist-info/DESCRIPTION.rst
Pyrebase-3.0.26.dist-info/METADATA
Pyrebase-3.0.26.dist-info/RECORD
Pyrebase-3.0.26.dist-info/WHEEL
Pyrebase-3.0.26.dist-info/metadata.json
Pyrebase-3.0.26.dist-info/top_level.txt
pyrebase/__init__.py
pyrebase/pyrebase.py
sseclient/__init__.py
sseclient/sseclient.py
