Metadata-Version: 1.1
Name: Pyrebase
Version: 3.0.26
Summary: A simple python wrapper for the Firebase API
Home-page: https://github.com/thisbejim/Pyrebase
Author: James Childs-Maidment
Author-email: UNKNOWN
License: MIT
Keywords: Firebase
Platform: UNKNOWN
Classifier: Development Status :: 3 - Alpha
Classifier: Intended Audience :: Developers
Classifier: License :: OSI Approved :: MIT License
Classifier: Programming Language :: Python :: 3.4
